gama/GamaClassifier.py
gama/GamaLongitudinalClassifier.py
gama/GamaPipeline.py
gama/GamaRegressor.py
gama/__init__.py
gama/__version__.py
gama/data_formatting.py
gama/data_loading.py
gama/gama.py
gama/configuration/__init__.py
gama/configuration/classification.py
gama/configuration/longitudinal_classification.py
gama/configuration/regression.py
gama/configuration/testconfiguration.py
gama/configuration/classification_task/__init__.py
gama/configuration/classification_task/classifiers.py
gama/configuration/classification_task/preprocessors.py
gama/configuration/configuration_task_test/__init__.py
gama/configuration/configuration_task_test/classifiers.py
gama/configuration/configuration_task_test/preprocessors.py
gama/configuration/longitudinal_classification_task/__init__.py
gama/configuration/longitudinal_classification_task/classifiers.py
gama/configuration/longitudinal_classification_task/data_preparation.py
gama/configuration/longitudinal_classification_task/preprocessors.py
gama/configuration/regression_task/__init__.py
gama/configuration/regression_task/preprocessors.py
gama/configuration/regression_task/regressors.py
gama/genetic_programming/__init__.py
gama/genetic_programming/crossover.py
gama/genetic_programming/mutation.py
gama/genetic_programming/nsga2.py
gama/genetic_programming/operations.py
gama/genetic_programming/operator_set.py
gama/genetic_programming/selection.py
gama/genetic_programming/compilers/__init__.py
gama/genetic_programming/compilers/scikitlearn.py
gama/genetic_programming/components/__init__.py
gama/genetic_programming/components/fitness.py
gama/genetic_programming/components/individual.py
gama/genetic_programming/components/primitive.py
gama/genetic_programming/components/primitive_node.py
gama/genetic_programming/components/terminal.py
gama/genetic_programming/longitudinal/constraints_longitudinal.py
gama/genetic_programming/longitudinal/crossover_longitudinal.py
gama/genetic_programming/longitudinal/mutation_longitudinal.py
auto_sklong-0.0.9.dist-info/METADATA
auto_sklong-0.0.9.dist-info/WHEEL
auto_sklong-0.0.9.dist-info/entry_points.txt
auto_sklong-0.0.9.dist-info/top_level.txt
auto_sklong-0.0.9.dist-info/RECORD
