Metadata-Version: 2.4
Name: Auto-Sklong
Version: 0.0.9
Summary: A package for automated machine learning based on scikit-learn and sklong to tackle the longitudinal machine learning classification tasks.
Author-email: Provost Simon <s.g.provost@kent.ac.uk>, Pieter Gijsbers <p.gijsbers@tue.nl>
License: MIT
Project-URL: Homepage, https://github.com/simonprovost/Auto-Sklong
Project-URL: Documentation, https://auto-sklong.readthedocs.io/en/latest/
Project-URL: Releases, https://github.com/simonprovost/auto-sklong/releases
Project-URL: Repository, https://github.com/simonprovost/Auto-Sklong
Project-URL: Issues, https://github.com/simonprovost/Auto-Sklong/issues
Project-URL: Scientific Paper, https://doi.org/10.1109/BIBM62325.2024.10821737
Classifier: License :: OSI Approved :: MIT License
Classifier: Programming Language :: Python :: 3
Requires-Python: <3.10,>=3.9
Requires-Dist: numpy==1.23.3
Requires-Dist: scipy>=1.5.0
Requires-Dist: pandas<2.0.0,>=1.5.3
Requires-Dist: stopit>=1.1.2
Requires-Dist: liac-arff>=2.2.2
Requires-Dist: category-encoders>=1.2.8
Requires-Dist: black>=23.10.1
Requires-Dist: psutil
Requires-Dist: configspace<1.0.0,>=0.7.1
Requires-Dist: smac==2.1.0
Requires-Dist: Scikit-longitudinal>=0.0.7
Requires-Dist: urllib3==1.26.6
